study_state_machine/__init__.py
study_state_machine/context.py
study_state_machine/errors.py
study_state_machine/interfaces.py
study_state_machine/study_states/__init__.py
study_state_machine/study_states/rna_seq.py
test/__init__.py
test/test_main.py
test/test_state_machine.py
study_state_machine-0.2.3.dist-info/LICENCE
study_state_machine-0.2.3.dist-info/METADATA
study_state_machine-0.2.3.dist-info/WHEEL
study_state_machine-0.2.3.dist-info/top_level.txt
study_state_machine-0.2.3.dist-info/RECORD
